testtool/__init__.py
testtool/tests.py
testsing-0.0.1.dist-info/LICENSE.txt
testsing-0.0.1.dist-info/METADATA
testsing-0.0.1.dist-info/WHEEL
testsing-0.0.1.dist-info/top_level.txt
testsing-0.0.1.dist-info/RECORD
