Metadata-Version: 2.1
Name: testsing
Version: 0.0.1
Summary: A useless test tool
Author: ZhangPeng
Author-email: apyizhidouzai@163.com
License-File: LICENSE.txt
